rack_pkg/__init__.py
rack_pkg/initialize_rack.py
rack_pkg/rack.py
ApiRack-0.1.1.dist-info/LICENSE
ApiRack-0.1.1.dist-info/METADATA
ApiRack-0.1.1.dist-info/WHEEL
ApiRack-0.1.1.dist-info/entry_points.txt
ApiRack-0.1.1.dist-info/top_level.txt
ApiRack-0.1.1.dist-info/RECORD
